{
  "device": {
    "vendor": "Dygma",
    "product": "Defy",
    "keyboardType": "wireless",
    "displayName": "Dygma Defy wireless",
    "urls": [
      {
        "name": "Homepage",
        "url": "https://www.dygma.com/defy/"
      }
    ]
  },
  "language": "english",
  "layerNames": [
    {
      "id": 0,
      "name": "L1"
    },
    {
      "id": 1,
      "name": "L2: Numpad"
    },
    {
      "id": 2,
      "name": "L3: Navigation"
    },
    {
      "id": 3,
      "name": "L4"
    },
    {
      "id": 4,
      "name": "L5"
    },
    {
      "id": 5,
      "name": "L6"
    },
    {
      "id": 6,
      "name": "L7"
    },
    {
      "id": 7,
      "name": "L8: System"
    },
    {
      "id": 8,
      "name": "L9"
    },
    {
      "id": 9,
      "name": "L10: Default backup"
    }
  ],
  "keymap": [
    {
      "keyCode": 41,
      "label": "ESC"
    },
    {
      "keyCode": 58,
      "label": "F1"
    },
    {
      "keyCode": 59,
      "label": "F2"
    },
    {
      "keyCode": 60,
      "label": "F3"
    },
    {
      "keyCode": 61,
      "label": "F4"
    },
    {
      "keyCode": 62,
      "label": "F5"
    },
    {
      "keyCode": 63,
      "label": "F6"
    },
    {
      "keyCode": 65535,
      "label": "",
      "extraLabel": "TRANS",
      "verbose": "Transparent"
    },
    {
      "keyCode": 65535,
      "label": "",
      "extraLabel": "TRANS",
      "verbose": "Transparent"
    },
    {
      "keyCode": 64,
      "label": "F7"
    },
    {
      "keyCode": 65,
      "label": "F8"
    },
    {
      "keyCode": 66,
      "label": "F9"
    },
    {
      "keyCode": 67,
      "label": "F10"
    },
    {
      "keyCode": 68,
      "label": "F11"
    },
    {
      "keyCode": 69,
      "label": "F12"
    },
    {
      "keyCode": 65535,
      "label": "",
      "extraLabel": "TRANS",
      "verbose": "Transparent"
    },
    {
      "keyCode": 65535,
      "label": "",
      "extraLabel": "TRANS",
      "verbose": "Transparent"
    },
    {
      "keyCode": 65535,
      "label": "",
      "extraLabel": "TRANS",
      "verbose": "Transparent"
    },
    {
      "keyCode": 65535,
      "label": "",
      "extraLabel": "TRANS",
      "verbose": "Transparent"
    },
    {
      "keyCode": 65535,
      "label": "",
      "extraLabel": "TRANS",
      "verbose": "Transparent"
    },
    {
      "keyCode": 65535,
      "label": "",
      "extraLabel": "TRANS",
      "verbose": "Transparent"
    },
    {
      "keyCode": 65535,
      "label": "",
      "extraLabel": "TRANS",
      "verbose": "Transparent"
    },
    {
      "keyCode": 65535,
      "label": "",
      "extraLabel": "TRANS",
      "verbose": "Transparent"
    },
    {
      "keyCode": 65535,
      "label": "",
      "extraLabel": "TRANS",
      "verbose": "Transparent"
    },
    {
      "keyCode": 65535,
      "label": "",
      "extraLabel": "TRANS",
      "verbose": "Transparent"
    },
    {
      "keyCode": 65535,
      "label": "",
      "extraLabel": "TRANS",
      "verbose": "Transparent"
    },
    {
      "keyCode": 65535,
      "label": "",
      "extraLabel": "TRANS",
      "verbose": "Transparent"
    },
    {
      "keyCode": 74,
      "label": "HOME"
    },
    {
      "keyCode": 77,
      "label": "END"
    },
    {
      "keyCode": 65535,
      "label": "",
      "extraLabel": "TRANS",
      "verbose": "Transparent"
    },
    {
      "keyCode": 65535,
      "label": "",
      "extraLabel": "TRANS",
      "verbose": "Transparent"
    },
    {
      "keyCode": 65535,
      "label": "",
      "extraLabel": "TRANS",
      "verbose": "Transparent"
    },
    {
      "keyCode": 65535,
      "label": "",
      "extraLabel": "TRANS",
      "verbose": "Transparent"
    },
    {
      "keyCode": 65535,
      "label": "",
      "extraLabel": "TRANS",
      "verbose": "Transparent"
    },
    {
      "keyCode": 65535,
      "label": "",
      "extraLabel": "TRANS",
      "verbose": "Transparent"
    },
    {
      "keyCode": 65535,
      "label": "",
      "extraLabel": "TRANS",
      "verbose": "Transparent"
    },
    {
      "keyCode": 65535,
      "label": "",
      "extraLabel": "TRANS",
      "verbose": "Transparent"
    },
    {
      "keyCode": 65535,
      "label": "",
      "extraLabel": "TRANS",
      "verbose": "Transparent"
    },
    {
      "keyCode": 65535,
      "label": "",
      "extraLabel": "TRANS",
      "verbose": "Transparent"
    },
    {
      "keyCode": 65535,
      "label": "",
      "extraLabel": "TRANS",
      "verbose": "Transparent"
    },
    {
      "keyCode": 65535,
      "label": "",
      "extraLabel": "TRANS",
      "verbose": "Transparent"
    },
    {
      "keyCode": 65535,
      "label": "",
      "extraLabel": "TRANS",
      "verbose": "Transparent"
    },
    {
      "keyCode": 80,
      "label": "←"
    },
    {
      "keyCode": 81,
      "label": "↓"
    },
    {
      "keyCode": 82,
      "label": "↑"
    },
    {
      "keyCode": 79,
      "label": "→"
    },
    {
      "keyCode": 65535,
      "label": "",
      "extraLabel": "TRANS",
      "verbose": "Transparent"
    },
    {
      "keyCode": 65535,
      "label": "",
      "extraLabel": "TRANS",
      "verbose": "Transparent"
    },
    {
      "keyCode": 65535,
      "label": "",
      "extraLabel": "TRANS",
      "verbose": "Transparent"
    },
    {
      "keyCode": 65535,
      "label": "",
      "extraLabel": "TRANS",
      "verbose": "Transparent"
    },
    {
      "keyCode": 65535,
      "label": "",
      "extraLabel": "TRANS",
      "verbose": "Transparent"
    },
    {
      "keyCode": 65535,
      "label": "",
      "extraLabel": "TRANS",
      "verbose": "Transparent"
    },
    {
      "keyCode": 65535,
      "label": "",
      "extraLabel": "TRANS",
      "verbose": "Transparent"
    },
    {
      "keyCode": 65535,
      "label": "",
      "extraLabel": "TRANS",
      "verbose": "Transparent"
    },
    {
      "keyCode": 65535,
      "label": "",
      "extraLabel": "TRANS",
      "verbose": "Transparent"
    },
    {
      "keyCode": 65535,
      "label": "",
      "extraLabel": "TRANS",
      "verbose": "Transparent"
    },
    {
      "keyCode": 65535,
      "label": "",
      "extraLabel": "TRANS",
      "verbose": "Transparent"
    },
    {
      "keyCode": 65535,
      "label": "",
      "extraLabel": "TRANS",
      "verbose": "Transparent"
    },
    {
      "keyCode": 65535,
      "label": "",
      "extraLabel": "TRANS",
      "verbose": "Transparent"
    },
    {
      "keyCode": 65535,
      "label": "",
      "extraLabel": "TRANS",
      "verbose": "Transparent"
    },
    {
      "keyCode": 75,
      "label": "PAGE UP",
      "verbose": "Page Up"
    },
    {
      "keyCode": 78,
      "label": "PAGE DOWN",
      "verbose": "Page Down"
    },
    {
      "keyCode": 65535,
      "label": "",
      "extraLabel": "TRANS",
      "verbose": "Transparent"
    },
    {
      "keyCode": 65535,
      "label": "",
      "extraLabel": "TRANS",
      "verbose": "Transparent"
    },
    {
      "keyCode": 65535,
      "label": "",
      "extraLabel": "TRANS",
      "verbose": "Transparent"
    },
    {
      "keyCode": 65535,
      "label": "",
      "extraLabel": "TRANS",
      "verbose": "Transparent"
    },
    {
      "keyCode": 20545,
      "label": "LEFT",
      "extraLabel": "M.Btn"
    },
    {
      "keyCode": 20546,
      "label": "RIGHT",
      "extraLabel": "M.Btn"
    },
    {
      "keyCode": 65535,
      "label": "",
      "extraLabel": "TRANS",
      "verbose": "Transparent"
    },
    {
      "keyCode": 65535,
      "label": "",
      "extraLabel": "TRANS",
      "verbose": "Transparent"
    },
    {
      "keyCode": 65535,
      "label": "",
      "extraLabel": "TRANS",
      "verbose": "Transparent"
    },
    {
      "keyCode": 65535,
      "label": "",
      "extraLabel": "TRANS",
      "verbose": "Transparent"
    },
    {
      "keyCode": 65535,
      "label": "",
      "extraLabel": "TRANS",
      "verbose": "Transparent"
    },
    {
      "keyCode": 65535,
      "label": "",
      "extraLabel": "TRANS",
      "verbose": "Transparent"
    },
    {
      "keyCode": 17492,
      "label": "1",
      "extraLabel": "LOCK"
    },
    {
      "keyCode": 65535,
      "label": "",
      "extraLabel": "TRANS",
      "verbose": "Transparent"
    },
    {
      "keyCode": 65535,
      "label": "",
      "extraLabel": "TRANS",
      "verbose": "Transparent"
    },
    {
      "keyCode": 20552,
      "label": "BACK",
      "extraLabel": "M.Btn"
    },
    {
      "keyCode": 20560,
      "label": "FORW.",
      "extraLabel": "M.Btn"
    },
    {
      "keyCode": 65535,
      "label": "",
      "extraLabel": "TRANS",
      "verbose": "Transparent"
    }
  ],
  "colormap": [
    11,
    6,
    6,
    6,
    6,
    6,
    6,
    15,
    15,
    15,
    15,
    15,
    15,
    15,
    15,
    15,
    15,
    15,
    15,
    15,
    15,
    15,
    15,
    15,
    15,
    15,
    15,
    15,
    15,
    1,
    1,
    15,
    15,
    15,
    15,
    15,
    6,
    6,
    6,
    6,
    6,
    6,
    15,
    15,
    15,
    13,
    13,
    15,
    15,
    15,
    15,
    14,
    14,
    14,
    14,
    15,
    15,
    15,
    13,
    13,
    15,
    15,
    15,
    1,
    1,
    15,
    15,
    2,
    15,
    15,
    1,
    1,
    1,
    1,
    1,
    1,
    1,
    1,
    1,
    1,
    1,
    14,
    14,
    14,
    14,
    1,
    1,
    1,
    1,
    1,
    1,
    1,
    1,
    1,
    1,
    1,
    1,
    1,
    1,
    1,
    14,
    14,
    1,
    1,
    1,
    1,
    1,
    1,
    1,
    1,
    1,
    1,
    1,
    1,
    1,
    1,
    1,
    1,
    1,
    1,
    1,
    1,
    1,
    1,
    1,
    1,
    1,
    1,
    1,
    1,
    1,
    1,
    1,
    1,
    14,
    14,
    14,
    14,
    1,
    1,
    1,
    1,
    1,
    1,
    1,
    1,
    1,
    1,
    1,
    1,
    1,
    1,
    1,
    14,
    14,
    1,
    1,
    1,
    1,
    1,
    1,
    1,
    1,
    1,
    1,
    1,
    1,
    1,
    1,
    1,
    1,
    1,
    1,
    1,
    1,
    1,
    1,
    15
  ],
  "palette": [
    {
      "r": 255,
      "g": 196,
      "b": 0,
      "rgb": "rgb(255, 196, 0)"
    },
    {
      "r": 163,
      "g": 248,
      "b": 171,
      "rgb": "rgb(163, 248, 171)"
    },
    {
      "r": 255,
      "g": 255,
      "b": 255,
      "rgb": "rgb(255, 255, 255)"
    },
    {
      "r": 250,
      "g": 255,
      "b": 0,
      "rgb": "rgb(250, 255, 0)"
    },
    {
      "r": 0,
      "g": 254,
      "b": 234,
      "rgb": "rgb(0, 254, 234)"
    },
    {
      "r": 0,
      "g": 51,
      "b": 255,
      "rgb": "rgb(0, 51, 255)"
    },
    {
      "r": 255,
      "g": 0,
      "b": 232,
      "rgb": "rgb(255, 0, 232)"
    },
    {
      "r": 87,
      "g": 164,
      "b": 255,
      "rgb": "rgb(87, 164, 255)"
    },
    {
      "r": 144,
      "g": 19,
      "b": 254,
      "rgb": "rgb(144, 19, 254)"
    },
    {
      "r": 156,
      "g": 186,
      "b": 255,
      "rgb": "rgb(156, 186, 255)"
    },
    {
      "r": 214,
      "g": 129,
      "b": 255,
      "rgb": "rgb(214, 129, 255)"
    },
    {
      "r": 255,
      "g": 9,
      "b": 0,
      "rgb": "rgb(255, 9, 0)"
    },
    {
      "r": 33,
      "g": 118,
      "b": 255,
      "rgb": "rgb(33, 118, 255)"
    },
    {
      "r": 255,
      "g": 180,
      "b": 0,
      "rgb": "rgb(255, 180, 0)"
    },
    {
      "r": 22,
      "g": 255,
      "b": 51,
      "rgb": "rgb(22, 255, 51)"
    },
    {
      "r": 0,
      "g": 0,
      "b": 0,
      "rgb": "rgb(0, 0, 0)"
    }
  ]
}